{
	"name": "django-tutoial",
	"dockerFile": "Dockerfile",
	"context": "..",
	"workspaceFolder": "/workspace",
	"mounts": ["source=${localWorkspaceFolder},target=/workspace,type=bind"],
	"remoteUser": "vscode",
	"customizations": {
		"vscode": {
			"settings": {
				// "python.pythonPath": "/workspace/server/.venv/bin/python",
				"python.linting.enabled": true,
				"python.formatting.provider": "black",
				"python.linting.pylintEnabled": true,
				"python.linting.mypyEnabled": true,
				"[python]": {
					"editor.formatOnSave": true,
					"editor.defaultFormatter": "ms-python.black-formatter"
				}
			},
			"extensions": [
				"mhutchie.git-graph",
				"GitHub.vscode-pull-request-github",
				"esbenp.prettier-vscode",
				"usernamehw.errorlens",
				"ms-python.python",
				"ms-python.vscode-pylance",
				"ms-python.black-formatter"
			]
		}
	}
}
